LICENSE.txt
MANIFEST.in
README.md
setup.py
starkcore/__init__.py
starkcore/environment.py
starkcore/error.py
starkcore/key.py
starkcore.egg-info/PKG-INFO
starkcore.egg-info/SOURCES.txt
starkcore.egg-info/dependency_links.txt
starkcore.egg-info/requires.txt
starkcore.egg-info/top_level.txt
starkcore/user/__init__.py
starkcore/user/__organization.py
starkcore/user/__project.py
starkcore/user/__publicuser.py
starkcore/user/__user.py
starkcore/utils/__init__.py
starkcore/utils/api.py
starkcore/utils/cache.py
starkcore/utils/case.py
starkcore/utils/checks.py
starkcore/utils/compatibility.py
starkcore/utils/enum.py
starkcore/utils/host.py
starkcore/utils/parse.py
starkcore/utils/request.py
starkcore/utils/resource.py
starkcore/utils/rest.py
starkcore/utils/subresource.py
starkcore/utils/url.py