Metadata-Version: 2.1
Name: starkcore
Version: 0.1.0
Summary: Basic SDK functionalities for the starkbank and starkinfra SDKs
Home-page: https://github.com/starkinfra/core-python
Author: Stark Infra
Author-email: developers@starkbank.com
License: MIT License
Platform: UNKNOWN
License-File: LICENSE.txt
